Getvalues/__init__.py
Getvalues/api.py
Getvalues/main.py
Getvalues-0.1.2.dist-info/LICENSE
Getvalues-0.1.2.dist-info/METADATA
Getvalues-0.1.2.dist-info/WHEEL
Getvalues-0.1.2.dist-info/top_level.txt
Getvalues-0.1.2.dist-info/RECORD
